kalmanfilterByRuhail/__init__.py
kalmanfilterByRuhail/core.py
kalmanfilterByRuhail/extended.py
kalmanfilterByRuhail/utils.py
kalmanfilterByRuhail/visualize.py
kalmanfilterByRuhail-0.1.1.dist-info/LICENSE.txt
kalmanfilterByRuhail-0.1.1.dist-info/METADATA
kalmanfilterByRuhail-0.1.1.dist-info/WHEEL
kalmanfilterByRuhail-0.1.1.dist-info/top_level.txt
kalmanfilterByRuhail-0.1.1.dist-info/RECORD
