Metadata-Version: 2.1
Name: kalmanfilterByRuhail
Version: 0.1.1
Summary: A Python library for implementing Kalman and Extended Kalman Filters
Home-page: https://github.com/ruhail-ali-khan/kalmanfilterByRuhail
Author: Ruhail Ali Khan
Author-email: ruhailalik@gmail.com
License: MIT
Classifier: Programming Language :: Python :: 3
Classifier: License :: OSI Approved :: MIT License
Classifier: Operating System :: OS Independent
Requires-Python: >=3.6
License-File: LICENSE.txt
Requires-Dist: numpy
Requires-Dist: matplotlib
